sower_androidemu/__init__.py
sower_androidemu/config.py
sower_androidemu/emulator.py
sower_androidemu/hooker.py
sower_androidemu/native_hook_utils.py
sower_androidemu/pcb.py
sower_androidemu/scheduler.py
sower_androidemu/const/__init__.py
sower_androidemu/const/android.py
sower_androidemu/const/emu_const.py
sower_androidemu/const/linux.py
sower_androidemu/cpu/__init__.py
sower_androidemu/cpu/interrupt_handler.py
sower_androidemu/cpu/syscall_handler.py
sower_androidemu/cpu/syscall_handlers.py
sower_androidemu/cpu/syscall_hooks.py
sower_androidemu/data/__init__.py
sower_androidemu/internal/__init__.py
sower_androidemu/internal/arm.py
sower_androidemu/internal/elf_reader.py
sower_androidemu/internal/module.py
sower_androidemu/internal/modules.py
sower_androidemu/java/__init__.py
sower_androidemu/java/constant_values.py
sower_androidemu/java/java_class_def.py
sower_androidemu/java/java_classloader.py
sower_androidemu/java/java_field_def.py
sower_androidemu/java/java_method_def.py
sower_androidemu/java/java_vm.py
sower_androidemu/java/jni_const.py
sower_androidemu/java/jni_env.py
sower_androidemu/java/jni_ref.py
sower_androidemu/java/jvm_id_conter.py
sower_androidemu/java/reference_table.py
sower_androidemu/java/classes/__init__.py
sower_androidemu/java/classes/activity_thread.py
sower_androidemu/java/classes/application.py
sower_androidemu/java/classes/array.py
sower_androidemu/java/classes/asset_manager.py
sower_androidemu/java/classes/bundle.py
sower_androidemu/java/classes/clazz.py
sower_androidemu/java/classes/constructor.py
sower_androidemu/java/classes/contentresolver.py
sower_androidemu/java/classes/context.py
sower_androidemu/java/classes/debug.py
sower_androidemu/java/classes/dexfile.py
sower_androidemu/java/classes/environment.py
sower_androidemu/java/classes/executable.py
sower_androidemu/java/classes/field.py
sower_androidemu/java/classes/file.py
sower_androidemu/java/classes/intent.py
sower_androidemu/java/classes/java_set.py
sower_androidemu-1.6.dist-info/METADATA
sower_androidemu-1.6.dist-info/WHEEL
sower_androidemu-1.6.dist-info/top_level.txt
sower_androidemu-1.6.dist-info/RECORD
